indsl/__init__.py
indsl/_version.py
indsl/create_translation_key.py
indsl/data_quality/__init__.py
indsl/data_quality/completeness.py
indsl/data_quality/datapoint_diff.py
indsl/data_quality/gaps_identification.py
indsl/data_quality/low_density_identification.py
indsl/data_quality/outliers.py
indsl/data_quality/rolling_stddev.py
indsl/data_quality/score/__init__.py
indsl/data_quality/score/accuracy/__init__.py
indsl/data_quality/score/base.py
indsl/data_quality/score/completeness/__init__.py
indsl/data_quality/score/completeness/density.py
indsl/data_quality/score/completeness/gap.py
indsl/data_quality/value_decrease_indication.py
indsl/data_quality/value_decrease_indication_v1.py
indsl/decorators.py
indsl/detect/__init__.py
indsl/detect/change_point_detector.py
indsl/detect/cusum.py
indsl/detect/drift_detector.py
indsl/detect/drift_detector_v1.py
indsl/detect/oscillation_detector.py
indsl/detect/steady_state.py
indsl/detect/unchanged_signal_detector.py
indsl/detect/utils.py
indsl/drilling/__init__.py
indsl/drilling/flag_detection.py
indsl/equipment/__init__.py
indsl/equipment/operational_availability_.py
indsl/equipment/pump_parameters.py
indsl/equipment/valve_parameters.py
indsl/equipment/valve_parameters_.py
indsl/equipment/volume_vessel.py
indsl/exceptions.py
indsl/filter/__init__.py
indsl/filter/simple_filters.py
indsl/filter/wavelet_filter.py
indsl/filter/wavelet_filter_v1.py
indsl/fluid_dynamics/__init__.py
indsl/fluid_dynamics/constants.py
indsl/fluid_dynamics/dimensionless.py
indsl/fluid_dynamics/friction.py
indsl/forecast/__init__.py
indsl/forecast/arma_predictor.py
indsl/forecast/holt_winters_predictor.py
indsl/not_listed_operations/__init__.py
indsl/not_listed_operations/deprecated_functions.py
indsl/not_listed_operations/utils.py
indsl/not_listed_operations/versioning_test.py
indsl/not_listed_operations/versioning_test_v1.py
indsl/oil_and_gas/__init__.py
indsl/oil_and_gas/engineering_calcs.py
indsl/oil_and_gas/gas_density_calcs.py
indsl-8.8.0.dist-info/METADATA
indsl-8.8.0.dist-info/WHEEL
indsl-8.8.0.dist-info/licenses/LICENSE
indsl-8.8.0.dist-info/RECORD
