Metadata-Version: 2.4
Name: indsl
Version: 8.8.0
Summary: Industrial Data Science Library by Cognite
License: Apache-2.0
License-File: LICENSE
Author: Cognite
Requires-Python: >=3.11,<3.14
Classifier: License :: OSI Approved :: Apache Software License
Classifier: Programming Language :: Python :: 3
Classifier: Programming Language :: Python :: 3.11
Classifier: Programming Language :: Python :: 3.12
Classifier: Programming Language :: Python :: 3.13
Classifier: Topic :: Scientific/Engineering
Provides-Extra: all
Provides-Extra: fluids
Provides-Extra: modeling
Provides-Extra: numba
Provides-Extra: plot
Provides-Extra: scikit
Provides-Extra: stats
Requires-Dist: csaps (>=1.1.0,<2.0.0) ; extra == "modeling" or extra == "all"
Requires-Dist: fluids (>=1.0.22,<2.0.0) ; extra == "fluids" or extra == "all"
Requires-Dist: kneed (>=0.8.0,<0.9.0) ; extra == "modeling" or extra == "all"
Requires-Dist: matplotlib (>=3.4.0,<4.0.0) ; extra == "plot" or extra == "all"
Requires-Dist: numba (>=0.61.0,<0.62.0) ; extra == "numba" or extra == "all"
Requires-Dist: numpy (>=2.0.0,<3.0.0)
Requires-Dist: packaging (>=23.0,<24.0)
Requires-Dist: pandas (>=2.3.0,<2.4.0)
Requires-Dist: pywavelets (>=1.6.0,<2.0.0)
Requires-Dist: scikit-image (>=0.25.0,<0.26.0) ; extra == "scikit" or extra == "all"
Requires-Dist: scikit-learn (>=1.3.0,<2.0.0) ; extra == "scikit" or extra == "all"
Requires-Dist: scipy (>=1.16.0,<1.17.0)
Requires-Dist: statsmodels (>=0.14.0,<0.15.0) ; extra == "stats" or extra == "all"
Requires-Dist: typeguard (>=4.0.0,<5.0.0)
Requires-Dist: typing-extensions (>=4.6.3,<5.0.0)
Project-URL: Documentation, https://indsl.docs.cognite.com
Project-URL: Homepage, https://indsl.docs.cognite.com
Project-URL: Repository, https://github.com/cognitedata/indsl
